smallperm-0.1.12.dist-info/METADATA
smallperm-0.1.12.dist-info/WHEEL
smallperm-0.1.12.dist-info/license_files/LICENSE
smallperm/extras.py
smallperm/wrapper.py
smallperm/__init__.py
smallperm/smallperm.abi3.so
smallperm-0.1.12.dist-info/RECORD
