Metadata-Version: 2.1
Name: smallperm
Version: 0.1.12
Classifier: Programming Language :: Rust
Classifier: Programming Language :: Python :: Implementation :: CPython
Classifier: Programming Language :: Python :: Implementation :: PyPy
License-File: LICENSE
Summary: Efficient O(1)-space pseudorandom permutation; high speed shuffling for large data
Author-email: RuneBlaze <runeblaze@protonmail.com>
Requires-Python: >=3.7
